adafruit_bluefruit_connect/__init__.py
adafruit_bluefruit_connect/_xyz_packet.py
adafruit_bluefruit_connect/accelerometer_packet.py
adafruit_bluefruit_connect/button_packet.py
adafruit_bluefruit_connect/color_packet.py
adafruit_bluefruit_connect/gyro_packet.py
adafruit_bluefruit_connect/location_packet.py
adafruit_bluefruit_connect/magnetometer_packet.py
adafruit_bluefruit_connect/packet.py
adafruit_bluefruit_connect/quaternion_packet.py
adafruit_bluefruit_connect/raw_text_packet.py
adafruit_circuitpython_bluefruitconnect-1.2.19.dist-info/licenses/LICENSE
adafruit_circuitpython_bluefruitconnect-1.2.19.dist-info/METADATA
adafruit_circuitpython_bluefruitconnect-1.2.19.dist-info/WHEEL
adafruit_circuitpython_bluefruitconnect-1.2.19.dist-info/top_level.txt
adafruit_circuitpython_bluefruitconnect-1.2.19.dist-info/RECORD
