Metadata-Version: 2.4
Name: adafruit-circuitpython-bluefruitconnect
Version: 1.2.19
Summary: CircuitPython library for use with the Adafruit Bluefruit Connect apps.
Author-email: Adafruit Industries <circuitpython@adafruit.com>
License: MIT
Project-URL: Homepage, https://github.com/adafruit/Adafruit_CircuitPython_BluefruitConnect
Keywords: adafruit,ble,bluefruit,bluetooth,micropython,circuitpython
Classifier: Intended Audience :: Developers
Classifier: Topic :: Software Development :: Libraries
Classifier: Topic :: Software Development :: Embedded Systems
Classifier: Topic :: System :: Hardware
Classifier: License :: OSI Approved :: MIT License
Classifier: Programming Language :: Python :: 3
License-File: LICENSE
Requires-Dist: Adafruit-Blinka
Provides-Extra: optional
Dynamic: license-file
